pybullet_industrial/__init__.py
pybullet_industrial/agv_robots.py
pybullet_industrial/collision_checker.py
pybullet_industrial/endeffector_tool.py
pybullet_industrial/extruder.py
pybullet_industrial/g_code_logger.py
pybullet_industrial/g_code_processor.py
pybullet_industrial/g_code_simplifier.py
pybullet_industrial/gripper.py
pybullet_industrial/interpolation.py
pybullet_industrial/joint_path.py
pybullet_industrial/material.py
pybullet_industrial/milling_tool.py
pybullet_industrial/path_builders.py
pybullet_industrial/raycaster.py
pybullet_industrial/remover.py
pybullet_industrial/robot_base.py
pybullet_industrial/sensors.py
pybullet_industrial/toolpath.py
pybullet_industrial/utility.py
pybullet_industrial-1.0.4.dist-info/METADATA
pybullet_industrial-1.0.4.dist-info/WHEEL
pybullet_industrial-1.0.4.dist-info/top_level.txt
pybullet_industrial-1.0.4.dist-info/RECORD
