Metadata-Version: 2.4
Name: pybullet_industrial
Version: 1.0.4
Summary: Pybullet_industrial is a process-aware robot simulation framework for pybullet.
Home-page: https://pybullet-industrial.readthedocs.io/en/latest/
Author: Jan Baumgärtner, Malte Hansjosten, Dominik Schönhofen
License: MIT
Requires-Dist: numpy<2.0.0
Requires-Dist: pybullet
Requires-Dist: scipy
Dynamic: author
Dynamic: description
Dynamic: home-page
Dynamic: license
Dynamic: requires-dist
Dynamic: summary
